{"upload_date": "20081209", "protocol": "https", "creator": null, "series": null, "format_note": "medium", "height": 360, "thumbnail": "https://i.ytimg.com/vi/pHOyfALe-Wc/hqdefault.jpg", "like_count": 2, "duration": 326, "fulltitle": "Legally Dead", "playlist_index": 69, "view_count": 133, "playlist": "Uploads from StoneColdFoxSketch", "title": "Legally Dead", "_filename": "B:\\Projects\\maude\\Stone_Cold_Fox\\Legally Dead.webm", "tags": ["legally", "dead", "ghost", "patrick", "swayze", "ghostbusters", "hunters", "ucb", "theatre", "sketch", "comedy", "stone", "cold", "fox", "maude", "night"], "is_live": null, "id": "pHOyfALe-Wc", "dislike_count": 0, "average_rating": 5.0, "abr": 128, "uploader_url": "http://www.youtube.com/user/StoneColdFoxSketch", "categories": ["Comedy"], "season_number": null, "annotations": null, "webpage_url_basename": "pHOyfALe-Wc", "acodec": "vorbis", "display_id": "pHOyfALe-Wc", "automatic_captions": {}, "description": "Legally Dead, written by Crystal Delahanty. Stone Cold Fox at Maude Night, UCBTNY, December 8, 2008. Starring Sean Clements, D'Arcy Erokan, and Cody Melton. Directed by Neil W. Casey.", "format": "43 - 640x360 (medium)", "start_time": null, "formats": [{"asr": 44100, "tbr": 95, "protocol": "https", "format": "140 - audio only (DASH audio)", "format_note": "DASH audio", "height": null, "preference": -50, "manifest_url": "https://manifest.googlevideo.com/api/manifest/dash/ip/98.113.67.7/itag/0/key/yt6/ipbits/0/signature/2CF1766A72EEA24EDF07BE40803803C35493ECDD.AE342BAFBDA4BEF568B7BBF42B2C98FCF25114ED/source/youtube/mm/31/mn/sn-8xgp1vo-xfgel/upn/hxsq1qYnBsc/hfr/1/mt/1492888648/mv/m/ms/au/playback_host/r7---sn-8xgp1vo-xfgel.googlevideo.com/ei/o6z7WJuPFI_78gTyoZ2QDA/id/a473b27c02def967/sparams/as%2Cei%2Chfr%2Cid%2Cinitcwndbps%2Cip%2Cipbits%2Citag%2Cmm%2Cmn%2Cms%2Cmv%2Cpl%2Cplayback_host%2Crequiressl%2Csource%2Cexpire/initcwndbps/2498750/as/fmp4_audio_clear%2Cfmp4_sd_hd_clear/expire/1492910339/pl/24/requiressl/yes", "format_id": "140", "container": "m4a_dash", "language": null, "http_headers": {"Accept-Charset": "ISO-8859-1,utf-8;q=0.7,*;q=0.7", "Accept-Language": "en-us,en;q=0.5", "Accept-Encoding": "gzip, deflate", "Accept": "text/html,application/xhtml+xml,application/xml;q=0.9,*/*;q=0.8", "User-Agent": "Mozilla/5.0 (X11; Linux x86_64; rv:10.0) Gecko/20150101 Firefox/47.0 (Chrome)"}, "url": "https://r7---sn-8xgp1vo-xfgel.googlevideo.com/videoplayback?id=a473b27c02def967&itag=140&source=youtube&requiressl=yes&mm=31&mn=sn-8xgp1vo-xfgel&mv=m&ms=au&ei=o6z7WJuPFI_78gTyoZ2QDA&initcwndbps=2498750&pl=24&ratebypass=yes&mime=audio/mp4&gir=yes&clen=3870163&lmt=1389596977515332&dur=325.659&key=dg_yt0&signature=12AD2AD9C515EFE9CF908758EDE52FE3D2B9A547.8F37F7401B261EAC5589F73449F2D0A57FED16B1&upn=hxsq1qYnBsc&mt=1492888648&ip=98.113.67.7&ipbits=0&expire=1492910339&sparams=ip,ipbits,expire,id,itag,source,requiressl,mm,mn,mv,ms,ei,initcwndbps,pl,ratebypass,mime,gir,clen,lmt,dur", "vcodec": "none", "ext": "m4a", "width": null, "abr": 128, "filesize": 3870163, "fps": null, "acodec": "mp4a.40.2"}, {"asr": null, "tbr": 110, "protocol": "https", "format": "160 - 192x144 (DASH video)", "format_note": "DASH video", "height": 144, "preference": -40, "manifest_url": "https://manifest.googlevideo.com/api/manifest/dash/ip/98.113.67.7/itag/0/key/yt6/ipbits/0/signature/2CF1766A72EEA24EDF07BE40803803C35493ECDD.AE342BAFBDA4BEF568B7BBF42B2C98FCF25114ED/source/youtube/mm/31/mn/sn-8xgp1vo-xfgel/upn/hxsq1qYnBsc/hfr/1/mt/1492888648/mv/m/ms/au/playback_host/r7---sn-8xgp1vo-xfgel.googlevideo.com/ei/o6z7WJuPFI_78gTyoZ2QDA/id/a473b27c02def967/sparams/as%2Cei%2Chfr%2Cid%2Cinitcwndbps%2Cip%2Cipbits%2Citag%2Cmm%2Cmn%2Cms%2Cmv%2Cpl%2Cplayback_host%2Crequiressl%2Csource%2Cexpire/initcwndbps/2498750/as/fmp4_audio_clear%2Cfmp4_sd_hd_clear/expire/1492910339/pl/24/requiressl/yes", "format_id": "160", "language": null, "http_headers": {"Accept-Charset": "ISO-8859-1,utf-8;q=0.7,*;q=0.7", "Accept-Language": "en-us,en;q=0.5", "Accept-Encoding": "gzip, deflate", "Accept": "text/html,application/xhtml+xml,application/xml;q=0.9,*/*;q=0.8", "User-Agent": "Mozilla/5.0 (X11; Linux x86_64; rv:10.0) Gecko/20150101 Firefox/47.0 (Chrome)"}, "url": "https://r7---sn-8xgp1vo-xfgel.googlevideo.com/videoplayback?id=a473b27c02def967&itag=160&source=youtube&requiressl=yes&mm=31&mn=sn-8xgp1vo-xfgel&mv=m&ms=au&ei=o6z7WJuPFI_78gTyoZ2QDA&initcwndbps=2498750&pl=24&ratebypass=yes&mime=video/mp4&gir=yes&clen=4314554&lmt=1389596956488269&dur=325.533&key=dg_yt0&signature=1E57E1AC06A16373831FD978814D0A2677F7308A.4DE07C00F4A0099ECE3C16CD66FBABD58FB3FE53&upn=hxsq1qYnBsc&mt=1492888648&ip=98.113.67.7&ipbits=0&expire=1492910339&sparams=ip,ipbits,expire,id,itag,source,requiressl,mm,mn,mv,ms,ei,initcwndbps,pl,ratebypass,mime,gir,clen,lmt,dur", "vcodec": "avc1.4d400c", "width": 192, "ext": "mp4", "filesize": 4314554, "fps": 15, "acodec": "none"}, {"asr": null, "tbr": 248, "protocol": "https", "format": "133 - 320x240 (DASH video)", "format_note": "DASH video", "height": 240, "preference": -40, "manifest_url": "https://manifest.googlevideo.com/api/manifest/dash/ip/98.113.67.7/itag/0/key/yt6/ipbits/0/signature/2CF1766A72EEA24EDF07BE40803803C35493ECDD.AE342BAFBDA4BEF568B7BBF42B2C98FCF25114ED/source/youtube/mm/31/mn/sn-8xgp1vo-xfgel/upn/hxsq1qYnBsc/hfr/1/mt/1492888648/mv/m/ms/au/playback_host/r7---sn-8xgp1vo-xfgel.googlevideo.com/ei/o6z7WJuPFI_78gTyoZ2QDA/id/a473b27c02def967/sparams/as%2Cei%2Chfr%2Cid%2Cinitcwndbps%2Cip%2Cipbits%2Citag%2Cmm%2Cmn%2Cms%2Cmv%2Cpl%2Cplayback_host%2Crequiressl%2Csource%2Cexpire/initcwndbps/2498750/as/fmp4_audio_clear%2Cfmp4_sd_hd_clear/expire/1492910339/pl/24/requiressl/yes", "format_id": "133", "language": null, "http_headers": {"Accept-Charset": "ISO-8859-1,utf-8;q=0.7,*;q=0.7", "Accept-Language": "en-us,en;q=0.5", "Accept-Encoding": "gzip, deflate", "Accept": "text/html,application/xhtml+xml,application/xml;q=0.9,*/*;q=0.8", "User-Agent": "Mozilla/5.0 (X11; Linux x86_64; rv:10.0) Gecko/20150101 Firefox/47.0 (Chrome)"}, "url": "https://r7---sn-8xgp1vo-xfgel.googlevideo.com/videoplayback?id=a473b27c02def967&itag=133&source=youtube&requiressl=yes&mm=31&mn=sn-8xgp1vo-xfgel&mv=m&ms=au&ei=o6z7WJuPFI_78gTyoZ2QDA&initcwndbps=2498750&pl=24&ratebypass=yes&mime=video/mp4&gir=yes&clen=9947757&lmt=1389596957390886&dur=325.533&key=dg_yt0&signature=67F3326891196966971B7EE89797AE3AD427E71A.75DA483F7411934480FD1194B4FFD7AD7BFE2F56&upn=hxsq1qYnBsc&mt=1492888648&ip=98.113.67.7&ipbits=0&expire=1492910339&sparams=ip,ipbits,expire,id,itag,source,requiressl,mm,mn,mv,ms,ei,initcwndbps,pl,ratebypass,mime,gir,clen,lmt,dur", "vcodec": "avc1.4d400d", "width": 320, "ext": "mp4", "filesize": 9947757, "fps": 30, "acodec": "none"}, {"http_headers": {"Accept-Charset": "ISO-8859-1,utf-8;q=0.7,*;q=0.7", "Accept-Language": "en-us,en;q=0.5", "Accept-Encoding": "gzip, deflate", "Accept": "text/html,application/xhtml+xml,application/xml;q=0.9,*/*;q=0.8", "User-Agent": "Mozilla/5.0 (X11; Linux x86_64; rv:10.0) Gecko/20150101 Firefox/47.0 (Chrome)"}, "protocol": "https", "format": "17 - 176x144 (small)", "url": "https://r7---sn-8xgp1vo-xfgel.googlevideo.com/videoplayback?itag=17&upn=-RQI-zeiyCc&dur=325.915&expire=1492910339&mime=video%2F3gpp&mv=m&pl=24&mt=1492888648&ms=au&id=o-ANinqP9WZ5JEhWt1LJTSIRl2Sm_gAWREMxcru1cjn56z&ei=oqz7WK6cNsOm8wSmwI2ACA&mn=sn-8xgp1vo-xfgel&source=youtube&mm=31&gir=yes&ip=98.113.67.7&lmt=1389597027710081&requiressl=yes&clen=3333357&sparams=clen%2Cdur%2Cei%2Cgir%2Cid%2Cinitcwndbps%2Cip%2Cipbits%2Citag%2Clmt%2Cmime%2Cmm%2Cmn%2Cms%2Cmv%2Cpl%2Crequiressl%2Csource%2Cupn%2Cexpire&initcwndbps=2498750&key=yt6&signature=A2DBA7E91CDCAAFABAF771C67A368C17F11719DB.36266D5F5E603042201DD759E5C967F6739E6FF4&ipbits=0&ratebypass=yes", "vcodec": "mp4v.20.3", "format_note": "small", "ext": "3gp", "player_url": null, "width": 176, "abr": 24, "format_id": "17", "height": 144, "resolution": "176x144", "acodec": "mp4a.40.2"}, {"http_headers": {"Accept-Charset": "ISO-8859-1,utf-8;q=0.7,*;q=0.7", "Accept-Language": "en-us,en;q=0.5", "Accept-Encoding": "gzip, deflate", "Accept": "text/html,application/xhtml+xml,application/xml;q=0.9,*/*;q=0.8", "User-Agent": "Mozilla/5.0 (X11; Linux x86_64; rv:10.0) Gecko/20150101 Firefox/47.0 (Chrome)"}, "protocol": "https", "format": "36 - 320x240 (small)", "url": "https://r7---sn-8xgp1vo-xfgel.googlevideo.com/videoplayback?itag=36&upn=-RQI-zeiyCc&dur=325.775&expire=1492910339&mime=video%2F3gpp&mv=m&pl=24&mt=1492888648&ms=au&id=o-ANinqP9WZ5JEhWt1LJTSIRl2Sm_gAWREMxcru1cjn56z&ei=oqz7WK6cNsOm8wSmwI2ACA&mn=sn-8xgp1vo-xfgel&source=youtube&mm=31&gir=yes&ip=98.113.67.7&lmt=1427190182936434&requiressl=yes&clen=9223611&sparams=clen%2Cdur%2Cei%2Cgir%2Cid%2Cinitcwndbps%2Cip%2Cipbits%2Citag%2Clmt%2Cmime%2Cmm%2Cmn%2Cms%2Cmv%2Cpl%2Crequiressl%2Csource%2Cupn%2Cexpire&initcwndbps=2498750&key=yt6&signature=5754FC5C9D4AF0CF316E815D501AFC7D7DD3DCAC.D9F6764059A143D42170F76B2F4A975DC18267B5&ipbits=0&ratebypass=yes", "vcodec": "mp4v.20.3", "format_note": "small", "height": 240, "width": 320, "ext": "3gp", "format_id": "36", "player_url": null, "resolution": "320x240", "acodec": "mp4a.40.2"}, {"http_headers": {"Accept-Charset": "ISO-8859-1,utf-8;q=0.7,*;q=0.7", "Accept-Language": "en-us,en;q=0.5", "Accept-Encoding": "gzip, deflate", "Accept": "text/html,application/xhtml+xml,application/xml;q=0.9,*/*;q=0.8", "User-Agent": "Mozilla/5.0 (X11; Linux x86_64; rv:10.0) Gecko/20150101 Firefox/47.0 (Chrome)"}, "protocol": "https", "format": "18 - 320x240 (medium)", "url": "https://r7---sn-8xgp1vo-xfgel.googlevideo.com/videoplayback?itag=18&upn=-RQI-zeiyCc&dur=325.659&expire=1492910339&mime=video%2Fmp4&mv=m&pl=24&mt=1492888648&ms=au&id=o-ANinqP9WZ5JEhWt1LJTSIRl2Sm_gAWREMxcru1cjn56z&ei=oqz7WK6cNsOm8wSmwI2ACA&mn=sn-8xgp1vo-xfgel&source=youtube&mm=31&gir=yes&ip=98.113.67.7&ratebypass=yes&lmt=1389596976519610&requiressl=yes&clen=13757800&sparams=clen%2Cdur%2Cei%2Cgir%2Cid%2Cinitcwndbps%2Cip%2Cipbits%2Citag%2Clmt%2Cmime%2Cmm%2Cmn%2Cms%2Cmv%2Cpl%2Cratebypass%2Crequiressl%2Csource%2Cupn%2Cexpire&initcwndbps=2498750&key=yt6&signature=918C8A4B4B8B12CAB0DE53A293F6EC14DA6F9DAB.272B7C36D5B7DE69E769713A6C3AF814E6D7B641&ipbits=0", "vcodec": "avc1.42001E", "format_note": "medium", "ext": "mp4", "player_url": null, "width": 320, "abr": 96, "format_id": "18", "height": 240, "resolution": "320x240", "acodec": "mp4a.40.2"}, {"http_headers": {"Accept-Charset": "ISO-8859-1,utf-8;q=0.7,*;q=0.7", "Accept-Language": "en-us,en;q=0.5", "Accept-Encoding": "gzip, deflate", "Accept": "text/html,application/xhtml+xml,application/xml;q=0.9,*/*;q=0.8", "User-Agent": "Mozilla/5.0 (X11; Linux x86_64; rv:10.0) Gecko/20150101 Firefox/47.0 (Chrome)"}, "protocol": "https", "format": "43 - 640x360 (medium)", "url": "https://r7---sn-8xgp1vo-xfgel.googlevideo.com/videoplayback?itag=43&upn=-RQI-zeiyCc&dur=0.000&expire=1492910339&mime=video%2Fwebm&mv=m&pl=24&mt=1492888648&ms=au&id=o-ANinqP9WZ5JEhWt1LJTSIRl2Sm_gAWREMxcru1cjn56z&ei=oqz7WK6cNsOm8wSmwI2ACA&mn=sn-8xgp1vo-xfgel&source=youtube&mm=31&gir=yes&ip=98.113.67.7&ratebypass=yes&lmt=1437447278645302&requiressl=yes&clen=9537705&sparams=clen%2Cdur%2Cei%2Cgir%2Cid%2Cinitcwndbps%2Cip%2Cipbits%2Citag%2Clmt%2Cmime%2Cmm%2Cmn%2Cms%2Cmv%2Cpl%2Cratebypass%2Crequiressl%2Csource%2Cupn%2Cexpire&initcwndbps=2498750&key=yt6&signature=6F766A36F5F911737E41924A9FF492CB28CC02AB.85E453AD917234C268B30ACB4CB8F9BCABACABC6&ipbits=0", "vcodec": "vp8.0", "format_note": "medium", "ext": "webm", "player_url": null, "width": 640, "abr": 128, "format_id": "43", "height": 360, "resolution": "640x360", "acodec": "vorbis"}], "playlist_id": "UUU9r7iXYdVBZUTj9J5Q8s9Q", "uploader": "StoneColdFoxSketch", "format_id": "43", "episode_number": null, "uploader_id": "StoneColdFoxSketch", "subtitles": {}, "playlist_title": "Uploads from StoneColdFoxSketch", "thumbnails": [{"url": "https://i.ytimg.com/vi/pHOyfALe-Wc/hqdefault.jpg", "id": "0"}], "license": "Standard YouTube License", "alt_title": null, "url": "https://r7---sn-8xgp1vo-xfgel.googlevideo.com/videoplayback?itag=43&upn=-RQI-zeiyCc&dur=0.000&expire=1492910339&mime=video%2Fwebm&mv=m&pl=24&mt=1492888648&ms=au&id=o-ANinqP9WZ5JEhWt1LJTSIRl2Sm_gAWREMxcru1cjn56z&ei=oqz7WK6cNsOm8wSmwI2ACA&mn=sn-8xgp1vo-xfgel&source=youtube&mm=31&gir=yes&ip=98.113.67.7&ratebypass=yes&lmt=1437447278645302&requiressl=yes&clen=9537705&sparams=clen%2Cdur%2Cei%2Cgir%2Cid%2Cinitcwndbps%2Cip%2Cipbits%2Citag%2Clmt%2Cmime%2Cmm%2Cmn%2Cms%2Cmv%2Cpl%2Cratebypass%2Crequiressl%2Csource%2Cupn%2Cexpire&initcwndbps=2498750&key=yt6&signature=6F766A36F5F911737E41924A9FF492CB28CC02AB.85E453AD917234C268B30ACB4CB8F9BCABACABC6&ipbits=0", "age_limit": 0, "vcodec": "vp8.0", "http_headers": {"Accept-Charset": "ISO-8859-1,utf-8;q=0.7,*;q=0.7", "Accept-Language": "en-us,en;q=0.5", "Accept-Encoding": "gzip, deflate", "Accept": "text/html,application/xhtml+xml,application/xml;q=0.9,*/*;q=0.8", "User-Agent": "Mozilla/5.0 (X11; Linux x86_64; rv:10.0) Gecko/20150101 Firefox/47.0 (Chrome)"}, "player_url": null, "ext": "webm", "extractor": "youtube", "end_time": null, "webpage_url": "https://www.youtube.com/watch?v=pHOyfALe-Wc", "extractor_key": "Youtube", "resolution": "640x360", "width": 640, "n_entries": 148}